Metadata-Version: 2.1
Name: pydiscordkit
Version: 1.1.0
Summary: A Discord Automation library that doesn't use the Official Discord API
Home-page: https://github.com/therealcyber71/pydiscordkit
Author: Sachit Ramesh
Author-email: quantechlxxi.corp@gmail.com
License: MIT
Project-URL: Issues, https://github.com/therealcyber71/pydiscordkit/issues
Keywords: automation,discord,pyautogui,browser
Platform: UNKNOWN
Classifier: Development Status :: 3 - Alpha
Classifier: Intended Audience :: Developers
Classifier: License :: OSI Approved :: MIT License
Classifier: Programming Language :: Python :: 3.8
Classifier: Programming Language :: Python :: 3.9
